odoo9_addon_module_auto_update-9.0.2.0.3-py2.7-nspkg.pth
odoo9_addon_module_auto_update-9.0.2.0.3.dist-info/DESCRIPTION.rst
odoo9_addon_module_auto_update-9.0.2.0.3.dist-info/METADATA
odoo9_addon_module_auto_update-9.0.2.0.3.dist-info/RECORD
odoo9_addon_module_auto_update-9.0.2.0.3.dist-info/WHEEL
odoo9_addon_module_auto_update-9.0.2.0.3.dist-info/metadata.json
odoo9_addon_module_auto_update-9.0.2.0.3.dist-info/namespace_packages.txt
odoo9_addon_module_auto_update-9.0.2.0.3.dist-info/top_level.txt
odoo_addons/module_auto_update/README.rst
odoo_addons/module_auto_update/__init__.py
odoo_addons/module_auto_update/__openerp__.py
odoo_addons/module_auto_update/addon_hash.py
odoo_addons/module_auto_update/hooks.py
odoo_addons/module_auto_update/data/cron_data_deprecated.xml
odoo_addons/module_auto_update/i18n/ca.po
odoo_addons/module_auto_update/i18n/de.po
odoo_addons/module_auto_update/i18n/es.po
odoo_addons/module_auto_update/i18n/es_MX.po
odoo_addons/module_auto_update/i18n/fr.po
odoo_addons/module_auto_update/i18n/hr.po
odoo_addons/module_auto_update/i18n/it.po
odoo_addons/module_auto_update/i18n/nl_NL.po
odoo_addons/module_auto_update/i18n/pt_BR.po
odoo_addons/module_auto_update/i18n/sl.po
odoo_addons/module_auto_update/i18n/tr.po
odoo_addons/module_auto_update/migrations/9.0.2.0.0/pre-migrate.py
odoo_addons/module_auto_update/models/__init__.py
odoo_addons/module_auto_update/models/module.py
odoo_addons/module_auto_update/models/module_deprecated.py
odoo_addons/module_auto_update/readme/CONFIGURE.rst
odoo_addons/module_auto_update/readme/CONTRIBUTORS.rst
odoo_addons/module_auto_update/readme/DESCRIPTION.rst
odoo_addons/module_auto_update/readme/ROADMAP.rst
odoo_addons/module_auto_update/readme/USAGE.rst
odoo_addons/module_auto_update/static/description/index.html
odoo_addons/module_auto_update/tests/__init__.py
odoo_addons/module_auto_update/tests/test_addon_hash.py
odoo_addons/module_auto_update/tests/test_module.py
odoo_addons/module_auto_update/tests/test_module_deprecated.py
odoo_addons/module_auto_update/tests/test_module_upgrade_deprecated.py
odoo_addons/module_auto_update/tests/sample_module/README.rst
odoo_addons/module_auto_update/tests/sample_module/data/f1.xml
odoo_addons/module_auto_update/tests/sample_module/data/f2.xml
odoo_addons/module_auto_update/tests/sample_module/i18n/en.po
odoo_addons/module_auto_update/tests/sample_module/i18n/en_US.po
